{
  "AudioBuffer": {
    "AudioBuffer()": {
      "type": "Constructor",
      "params": [],
      "returns": "",
      "inherits": []
    },
    "duration": {
      "type": "InstanceProperty",
      "params": [],
      "returns": "",
      "inherits": []
    },
    "length": {
      "type": "InstanceProperty",
      "params": [],
      "returns": "",
      "inherits": []
    },
    "numberOfChannels": {
      "type": "InstanceProperty",
      "params": [],
      "returns": "",
      "inherits": []
    },
    "sampleRate": {
      "type": "InstanceProperty",
      "params": [],
      "returns": "",
      "inherits": []
    },
    "copyFromChannel()": {
      "type": "InstanceMethod",
      "params": [],
      "returns": "",
      "inherits": []
    },
    "copyToChannel()": {
      "type": "InstanceMethod",
      "params": [],
      "returns": "",
      "inherits": []
    },
    "getChannelData()": {
      "type": "InstanceMethod",
      "params": [],
      "returns": "",
      "inherits": []
    }
  }
}