{
  "RTCRemoteInboundRtpStreamStats": {
    "codecId": {
      "type": "InstanceProperty",
      "params": [],
      "returns": "",
      "inherits": []
    },
    "fractionLost": {
      "type": "InstanceProperty",
      "params": [],
      "returns": "",
      "inherits": []
    },
    "id": {
      "type": "InstanceProperty",
      "params": [],
      "returns": "",
      "inherits": []
    },
    "jitter": {
      "type": "InstanceProperty",
      "params": [],
      "returns": "",
      "inherits": []
    },
    "kind": {
      "type": "InstanceProperty",
      "params": [],
      "returns": "",
      "inherits": []
    },
    "localId": {
      "type": "InstanceProperty",
      "params": [],
      "returns": "",
      "inherits": []
    },
    "packetsLost": {
      "type": "InstanceProperty",
      "params": [],
      "returns": "",
      "inherits": []
    },
    "roundTripTime": {
      "type": "InstanceProperty",
      "params": [],
      "returns": "",
      "inherits": []
    },
    "roundTripTimeMeasurements": {
      "type": "InstanceProperty",
      "params": [],
      "returns": "",
      "inherits": []
    },
    "ssrc": {
      "type": "InstanceProperty",
      "params": [],
      "returns": "",
      "inherits": []
    },
    "timestamp": {
      "type": "InstanceProperty",
      "params": [],
      "returns": "",
      "inherits": []
    },
    "totalRoundTripTime": {
      "type": "InstanceProperty",
      "params": [],
      "returns": "",
      "inherits": []
    },
    "transportId": {
      "type": "InstanceProperty",
      "params": [],
      "returns": "",
      "inherits": []
    },
    "type": {
      "type": "InstanceProperty",
      "params": [],
      "returns": "",
      "inherits": []
    }
  }
}