{
  "XMLHttpRequestUpload": {
    "abort": {
      "type": "Event",
      "params": [],
      "returns": "",
      "inherits": []
    },
    "error": {
      "type": "Event",
      "params": [],
      "returns": "",
      "inherits": []
    },
    "load": {
      "type": "Event",
      "params": [],
      "returns": "",
      "inherits": []
    },
    "loadend": {
      "type": "Event",
      "params": [],
      "returns": "",
      "inherits": []
    },
    "loadstart": {
      "type": "Event",
      "params": [],
      "returns": "",
      "inherits": []
    },
    "progress": {
      "type": "Event",
      "params": [],
      "returns": "",
      "inherits": []
    },
    "timeout": {
      "type": "Event",
      "params": [],
      "returns": "",
      "inherits": []
    },
    "XMLHttpRequestEventTarget": {
      "type": "Inheritance",
      "params": [],
      "returns": "",
      "inherits": []
    },
    "EventTarget": {
      "type": "Inheritance",
      "params": [],
      "returns": "",
      "inherits": []
    }
  }
}