{
  "XRInputSource": {
    "gamepad": {
      "type": "InstanceProperty",
      "params": [],
      "returns": "",
      "inherits": []
    },
    "gripSpace": {
      "type": "InstanceProperty",
      "params": [],
      "returns": "",
      "inherits": []
    },
    "hand": {
      "type": "InstanceProperty",
      "params": [],
      "returns": "",
      "inherits": []
    },
    "handedness": {
      "type": "InstanceProperty",
      "params": [],
      "returns": "",
      "inherits": []
    },
    "profiles": {
      "type": "InstanceProperty",
      "params": [],
      "returns": "",
      "inherits": []
    },
    "targetRayMode": {
      "type": "InstanceProperty",
      "params": [],
      "returns": "",
      "inherits": []
    },
    "targetRaySpace": {
      "type": "InstanceProperty",
      "params": [],
      "returns": "",
      "inherits": []
    }
  }
}