{
  "XRReferenceSpace": {
    "getOffsetReferenceSpace()": {
      "type": "InstanceMethod",
      "params": [],
      "returns": "",
      "inherits": []
    },
    "reset": {
      "type": "Event",
      "params": [],
      "returns": "",
      "inherits": []
    },
    "XRSpace": {
      "type": "Inheritance",
      "params": [],
      "returns": "",
      "inherits": []
    },
    "EventTarget": {
      "type": "Inheritance",
      "params": [],
      "returns": "",
      "inherits": []
    }
  }
}